[{"id":4407471,"type":"Laliga","team_a_logo":"https://i.postimg.cc/MGXV3bhf/image-search-1737132077725.png","team_b_logo":"https://i.postimg.cc/MGXV3bhf/image-search-1737132077725.png","team_a_name":"All matches","team_b_name":"All matches","tournament_name":"Football","link_id":"1746946317959","published":1,"startTime":1747328400000},{"id":4407480,"type":"Bangladesh vs South Africa","team_a_logo":"https://i.postimg.cc/qMZRVk9K/image-search-1737749109759.webp","team_b_logo":"https://i.postimg.cc/tRDMmzCd/1000187457.webp","team_a_name":"Bangladesh","team_b_name":"South Africa","tournament_name":"Cricket","link_id":"1747028435911","published":0,"startTime":1747215900000},{"id":4407481,"type":"Bangladesh A vs New Zealand A","team_a_logo":"https://i.postimg.cc/qMZRVk9K/image-search-1737749109759.webp","team_b_logo":"https://i.postimg.cc/G3Nk2BMw/20250305-010633.webp","team_a_name":"Bangladesh","team_b_name":"New Zealand","tournament_name":"Cricket","link_id":"1747216496919","published":0,"startTime":1747216800000},{"id":4407492,"type":"ICC CWC league 2","team_a_logo":"https://i.postimg.cc/c4FHsMxy/images-3.png","team_b_logo":"https://i.postimg.cc/pXWrb1tJ/images-5.jpg","team_a_name":"Scotland","team_b_name":"Netherlands","tournament_name":"Football","link_id":"1747371427951","published":0,"startTime":1747386000000},{"id":4407493,"type":"Saudi Pro league","team_a_logo":"https://i.postimg.cc/RVkSzcw1/images-7.jpg","team_b_logo":"https://i.postimg.cc/bNV9Z9mQ/download-4.png","team_a_name":"Al fateh","team_b_name":"Al hilal","tournament_name":"Football","link_id":"1747371675782","published":0,"startTime":1747410900000},{"id":4407494,"type":"Saudi Pro League match 2","team_a_logo":"https://i.postimg.cc/tJ2tt3pG/images-1.png","team_b_logo":"https://i.postimg.cc/66G6bjv6/download.png","team_a_name":"Al orobah","team_b_name":"Al Khaleej","tournament_name":"Football","link_id":"1747374272270","published":0,"startTime":1747413600000}]